votekit/__init__.py
votekit/ballot.py
votekit/ballot_generator/__init__.py
votekit/ballot_generator/ballot_generator.py
votekit/ballot_generator/bloc_slate_generator/__init__.py
votekit/ballot_generator/bloc_slate_generator/cambridge.py
votekit/ballot_generator/bloc_slate_generator/cumulative.py
votekit/ballot_generator/bloc_slate_generator/data/Cambridge_09to17_ballot_types.p
votekit/ballot_generator/bloc_slate_generator/model.py
votekit/ballot_generator/bloc_slate_generator/name_bradley_terry.py
votekit/ballot_generator/bloc_slate_generator/name_plackett_luce.py
votekit/ballot_generator/bloc_slate_generator/slate_bradley_terry.py
votekit/ballot_generator/bloc_slate_generator/slate_plackett_luce.py
votekit/ballot_generator/bloc_slate_generator/slate_utils.py
votekit/ballot_generator/deprecated_classes.py
votekit/ballot_generator/std_generator/__init__.py
votekit/ballot_generator/std_generator/impartial_anon_culture.py
votekit/ballot_generator/std_generator/impartial_culture.py
votekit/ballot_generator/std_generator/spacial.py
votekit/ballot_generator/utils.py
votekit/cleaning/__init__.py
votekit/cleaning/rank_ballots_cleaning.py
votekit/cleaning/rank_profiles_cleaning.py
votekit/cleaning/score_ballots_cleaning.py
votekit/cleaning/score_profiles_cleaning.py
votekit/cvr_loaders/__init__.py
votekit/cvr_loaders/load_ranking_csv.py
votekit/cvr_loaders/load_scottish.py
votekit/elections/__init__.py
votekit/elections/election_state.py
votekit/elections/election_types/__init__.py
votekit/elections/election_types/approval/__init__.py
votekit/elections/election_types/approval/approval.py
votekit/elections/election_types/ranking/__init__.py
votekit/elections/election_types/ranking/abstract_ranking.py
votekit/elections/election_types/ranking/alaska.py
votekit/elections/election_types/ranking/boosted_random_dictator.py
votekit/elections/election_types/ranking/borda.py
votekit/elections/election_types/ranking/condo_borda.py
votekit-3.3.0.dist-info/LICENSE
votekit-3.3.0.dist-info/METADATA
votekit-3.3.0.dist-info/WHEEL
votekit-3.3.0.dist-info/RECORD
