Metadata-Version: 2.3
Name: votekit
Version: 3.3.0
Summary: A Swiss army knife for computational social choice research.
Author: MGGG
Author-email: code@mggg.org
Requires-Python: >=3.11, <3.14
Classifier: Programming Language :: Python :: 3
Classifier: Programming Language :: Python :: 3.11
Classifier: Programming Language :: Python :: 3.12
Classifier: Programming Language :: Python :: 3.13
Requires-Dist: apportionment (>=1.0,<2.0)
Requires-Dist: jinja2 (>=3.1.6,<4.0)
Requires-Dist: matplotlib (>=3.10.5,<4.0)
Requires-Dist: mypy (==1.18.2)
Requires-Dist: mypy-extensions (>=1.1.0)
Requires-Dist: networkx (>=3.5,<4.0)
Requires-Dist: numba (>=0.62.1,<0.62.2)
Requires-Dist: numpy (>=2.3.3,<3.0)
Requires-Dist: pandas (>2.2)
Requires-Dist: psutil (>=7.1.0,<8.0.0)
Requires-Dist: pydantic (>=2.11.9,<3.0)
Requires-Dist: scikit-learn (>=1.7.1,<2.0)
Requires-Dist: scipy (>=1.16.1,<2.0)
Requires-Dist: seaborn (>=0.13.2,<0.14.0)
Requires-Dist: types-networkx (>=3.5.0.20250728,<4.0.0.0)
Requires-Dist: types-psutil (>=7.0.0.20250822,<8.0.0.0)
Requires-Dist: types-seaborn (>=0.13.2.20250728,<0.14.0.0)
Project-URL: Repository, https://github.com/mggg/VoteKit
